deemix/__init__.py
deemix/__main__.py
deemix/decryption.py
deemix/downloader.py
deemix/errors.py
deemix/itemgen.py
deemix/settings.py
deemix/tagger.py
deemix/plugins/__init__.py
deemix/plugins/spotify.py
deemix/types/Album.py
deemix/types/Artist.py
deemix/types/Date.py
deemix/types/DownloadObjects.py
deemix/types/Lyrics.py
deemix/types/Picture.py
deemix/types/Playlist.py
deemix/types/Track.py
deemix/types/__init__.py
deemix/utils/__init__.py
deemix/utils/crypto.py
deemix/utils/deezer.py
deemix/utils/localpaths.py
deemix/utils/pathtemplates.py
deemix-3.6.6.dist-info/LICENSE.txt
deemix-3.6.6.dist-info/METADATA
deemix-3.6.6.dist-info/WHEEL
deemix-3.6.6.dist-info/entry_points.txt
deemix-3.6.6.dist-info/top_level.txt
deemix-3.6.6.dist-info/RECORD
