Metadata-Version: 2.1
Name: deemix
Version: 3.6.6
Summary: A barebone deezer downloader library
Home-page: UNKNOWN
Author: RemixDev
Author-email: RemixDev64@gmail.com
License: GPL3
Platform: UNKNOWN
Classifier: License :: OSI Approved :: GNU General Public License v3 (GPLv3)
Classifier: Programming Language :: Python :: 3 :: Only
Classifier: Programming Language :: Python :: 3.7
Classifier: Operating System :: OS Independent
Requires-Python: >=3.7
Provides-Extra: spotify
License-File: LICENSE.txt
